firecrawl_tools/__init__.py
firecrawl_tools/cli.py
firecrawl_tools/config.py
firecrawl_tools/core.py
firecrawl_tools/exceptions.py
firecrawl_tools/tools.py
firecrawl_tools-0.1.1.dist-info/METADATA
firecrawl_tools-0.1.1.dist-info/WHEEL
firecrawl_tools-0.1.1.dist-info/entry_points.txt
firecrawl_tools-0.1.1.dist-info/licenses/LICENSE
firecrawl_tools-0.1.1.dist-info/RECORD
