Metadata-Version: 2.4
Name: firecrawl-tools
Version: 0.1.1
Summary: A comprehensive collection of async tools for web scraping, searching, and data extraction using the Firecrawl API
Project-URL: Homepage, https://github.com/ichbineshan/firecrawl-tools-py
Project-URL: Documentation, https://github.com/ichbineshan/firecrawl-tools-py#readme
Project-URL: Repository, https://github.com/ichbineshan/firecrawl-tools-py
Project-URL: Bug Tracker, https://github.com/ichbineshan/firecrawl-tools-py/issues
Project-URL: Changelog, https://github.com/ichbineshan/firecrawl-tools-py/blob/main/CHANGELOG.md
Author-email: Eshan Pandey <eshanpandeyy@gmail.com>
Maintainer-email: Eshan Pandey <eshanpandeyy@gmail.com>
License: MIT
License-File: LICENSE
Keywords: ai,async,firecrawl,langchain,tools,web-scraping
Classifier: Development Status :: 4 - Beta
Classifier: Intended Audience :: Developers
Classifier: License :: OSI Approved :: MIT License
Classifier: Operating System :: OS Independent
Classifier: Programming Language :: Python :: 3
Classifier: Programming Language :: Python :: 3.8
Classifier: Programming Language :: Python :: 3.9
Classifier: Programming Language :: Python :: 3.10
Classifier: Programming Language :: Python :: 3.11
Classifier: Programming Language :: Python :: 3.12
Classifier: Topic :: Internet :: WWW/HTTP
Classifier: Topic :: Software Development :: Libraries :: Python Modules
Classifier: Topic :: Text Processing :: Markup :: HTML
Requires-Python: >=3.8
Requires-Dist: firecrawl>=0.1.0
Requires-Dist: langchain-core>=0.1.0
Requires-Dist: pydantic>=2.0.0
Provides-Extra: dev
Requires-Dist: black>=23.0.0; extra == 'dev'
Requires-Dist: flake8>=6.0.0; extra == 'dev'
Requires-Dist: isort>=5.12.0; extra == 'dev'
Requires-Dist: mypy>=1.0.0; extra == 'dev'
Requires-Dist: pre-commit>=3.0.0; extra == 'dev'
Requires-Dist: pytest-asyncio>=0.21.0; extra == 'dev'
Requires-Dist: pytest-cov>=4.0.0; extra == 'dev'
Requires-Dist: pytest>=7.0.0; extra == 'dev'
Provides-Extra: docs
Requires-Dist: myst-parser>=1.0.0; extra == 'docs'
Requires-Dist: sphinx-rtd-theme>=1.2.0; extra == 'docs'
Requires-Dist: sphinx>=6.0.0; extra == 'docs'
